{
  "trace_id": "01f1b56d-7561-44a4-a49a-e29379917101",
  "ts": 1779816198.500362,
  "sender_id": "whatsapp:+559999999999",
  "user_message": "Tudo bem?",
  "events": [
    {
      "stage": "input",
      "module": "main",
      "function": "eldora_primary_runtime_reply",
      "input_preview": "Tudo bem?",
      "output_preview": "Tudo certo por aqui 🙂 E você?",
      "leaks": [],
      "extra": {}
    },
    {
      "stage": "humanized",
      "module": "main",
      "function": "eldora_primary_runtime_reply",
      "input_preview": "Tudo certo por aqui 🙂 E você?",
      "output_preview": "Tudo certo por aqui 🙂 E você?",
      "leaks": [],
      "extra": {}
    },
    {
      "stage": "final_output",
      "module": "main",
      "function": "eldora_primary_runtime_reply",
      "input_preview": "Tudo certo por aqui 🙂 E você?",
      "output_preview": "Tudo certo por aqui 🙂 E você?",
      "leaks": [],
      "extra": {}
    }
  ]
}