{
  "trace_id": "b85f0ac2-ef0d-4d75-aad9-f2229a7206d8",
  "ts": 1779817771.8697948,
  "sender_id": "whatsapp:+559999999999",
  "user_message": "Como você está?",
  "events": [
    {
      "stage": "input",
      "module": "main",
      "function": "eldora_primary_runtime_reply",
      "input_preview": "Como você está?",
      "output_preview": "Tudo certo por aqui 🙂 E você?",
      "leaks": [],
      "extra": {}
    },
    {
      "stage": "humanized",
      "module": "main",
      "function": "eldora_primary_runtime_reply",
      "input_preview": "Tudo certo por aqui 🙂 E você?",
      "output_preview": "Tudo certo por aqui 🙂 E você?",
      "leaks": [],
      "extra": {}
    },
    {
      "stage": "duplicate_blocked",
      "module": "main",
      "function": "eldora_primary_runtime_reply",
      "input_preview": "Tudo certo por aqui 🙂 E você?",
      "output_preview": "",
      "leaks": [],
      "extra": {}
    }
  ]
}